setup.py
pyIncomingSlack/__init__.py
pyIncomingSlack/pyIncomingSlack.py
pyIncomingSlack.egg-info/PKG-INFO
pyIncomingSlack.egg-info/SOURCES.txt
pyIncomingSlack.egg-info/dependency_links.txt
pyIncomingSlack.egg-info/entry_points.txt
pyIncomingSlack.egg-info/top_level.txt