Metadata-Version: 1.0
Name: pyIncomingSlack
Version: 0.1
Summary: Post to Slack Channel/Groups using "Incoming WebHooks"
Home-page: https://github.com/t-ichii/pyIncomingSlack
Author: Takeru Ichii
Author-email: takeru.ichii@facebook.com
License: UNKNOWN
Platform: UNKNOWN
